pre_commit_pylint_wrapper.py
pre_commit_pylint_wrapper_pythonpath-0.0.0.dist-info/METADATA
pre_commit_pylint_wrapper_pythonpath-0.0.0.dist-info/WHEEL
pre_commit_pylint_wrapper_pythonpath-0.0.0.dist-info/entry_points.txt
pre_commit_pylint_wrapper_pythonpath-0.0.0.dist-info/top_level.txt
pre_commit_pylint_wrapper_pythonpath-0.0.0.dist-info/RECORD
