Metadata-Version: 2.1
Name: pre-commit-pylint-wrapper-pythonpath
Version: 0.0.0
Summary: UNKNOWN
Home-page: UNKNOWN
License: UNKNOWN
Platform: UNKNOWN
Requires-Python: >=3.4
Requires-Dist: pylint (==2.3.1)
